kismet_fortune/__init__.py
kismet_fortune/__main__.py
kismet_fortune-0.1.0.dist-info/LICENSE
kismet_fortune-0.1.0.dist-info/METADATA
kismet_fortune-0.1.0.dist-info/WHEEL
kismet_fortune-0.1.0.dist-info/RECORD
