Metadata-Version: 2.3
Name: kismet-fortune
Version: 0.1.0
Summary: An evolutionary take on fortune-mod.
License: GPL3.0
Author: Steven Miklovic
Author-email: steven@thinkingsage.com
Requires-Python: >=3.7,>=3.9,<=3.11
Classifier: License :: Other/Proprietary License
Classifier: Programming Language :: Python :: 3
Classifier: Programming Language :: Python :: 3.9
Classifier: Programming Language :: Python :: 3.10
Classifier: Programming Language :: Python :: 3.11
Requires-Dist: google-genai (>=0.5.0,<0.6.0)
Requires-Dist: prompt-toolkit (>=3.0.48,<4.0.0)
Requires-Dist: typer (>=0.15.1,<0.16.0)
